datrics_json/__init__.py
datrics_json/core_model/__init__.py
datrics_json/core_model/classification.py
datrics_json/core_model/regression.py
datrics_json/core_model/unsupervized.py
datrics_json/serialization/__init__.py
datrics_json/serialization/json_serialization_classifiers.py
datrics_json/serialization/json_serialization_clustering.py
datrics_json/serialization/json_serialization_regressors.py
datrics_model_json/__init__.py
datrics_model_json/core_model/__init__.py
datrics_model_json/core_model/classification.py
datrics_model_json/core_model/regression.py
datrics_model_json/core_model/unsupervized.py
datrics_model_json/serialization/__init__.py
datrics_model_json/serialization/json_serialization_classifiers.py
datrics_model_json/serialization/json_serialization_clustering.py
datrics_model_json/serialization/json_serialization_regressors.py
datrics_json-0.0.1.dist-info/LICENSE
datrics_json-0.0.1.dist-info/METADATA
datrics_json-0.0.1.dist-info/WHEEL
datrics_json-0.0.1.dist-info/dependency_links.txt
datrics_json-0.0.1.dist-info/top_level.txt
datrics_json-0.0.1.dist-info/RECORD
