Metadata-Version: 2.1
Name: datrics-json
Version: 0.0.1
Summary: Open source library for the Datrics models deserialization
Home-page: https://github.com/datrics-ai/datrics-json
Author-email: th@datrics.ai
License: MIT
Platform: UNKNOWN
Classifier: Programming Language :: Python :: 3
Classifier: License :: OSI Approved :: MIT License
Classifier: Operating System :: OS Independent
Requires-Python: >=3.5
Requires-Dist: scikit-learn (>=0.22.0)
Requires-Dist: pandas (>=1.0.3)
Requires-Dist: lightgbm (>=2.3.0)
Requires-Dist: numpy (>=1.18.0)
